twol/__init__.py
twol/aligner.py
twol/alphabet.py
twol/cfg.py
twol/discopars.py
twol/discover.py
twol/fs.py
twol/histdiscov.py
twol/lexc2dot.py
twol/metric.py
twol/multialign.py
twol/raw2named.py
twol/table2words.py
twol/tester.py
twol/twbt.py
twol/twexamp.py
twol/twolcomp.py
twol/twolcsyntax.ebnf
twol/twparser.py
twol/twrule.py
twol/words2zerofilled.py
twol/zerofilled2raw.py
twol-0.9.dist-info/LICENSE.txt
twol-0.9.dist-info/METADATA
twol-0.9.dist-info/WHEEL
twol-0.9.dist-info/entry_points.txt
twol-0.9.dist-info/top_level.txt
twol-0.9.dist-info/RECORD
