Metadata-Version: 2.1
Name: twol
Version: 0.9
Summary: Tools for simplified two-level morphology
Home-page: https://github.com/koskenni/twol
Author: Kimmo Koskenniemi
Author-email: koskenni@gmail.com
License: UNKNOWN
Platform: UNKNOWN
Classifier: Programming Language :: Python :: 3
Classifier: License :: OSI Approved :: GNU General Public License v3 or later (GPLv3+)
Classifier: Operating System :: OS Independent
Requires-Python: >=3.8
License-File: LICENSE.txt
Requires-Dist: TatSu==5.7.4
Requires-Dist: grapheme
Requires-Dist: hfst>=3.15
